{
    "key": "group_6530e5259c0aa",
    "title": "Theme Options",
    "fields": [
        {
            "key": "field_6530ebf032adb",
            "label": "General",
            "name": "",
            "aria-label": "",
            "type": "tab",
            "instructions": "",
            "required": 0,
            "conditional_logic": 0,
            "wrapper": {
                "width": "",
                "class": "",
                "id": ""
            },
            "placement": "top",
            "endpoint": 0,
            "selected": 0
        },
        {
            "key": "field_653c7ca45302e",
            "label": "Site Information",
            "name": "site_information",
            "aria-label": "",
            "type": "group",
            "instructions": "",
            "required": 0,
            "conditional_logic": 0,
            "wrapper": {
                "width": "",
                "class": "",
                "id": ""
            },
            "layout": "block",
            "sub_fields": [
                {
                    "key": "field_6530ec25ca52a",
                    "label": "Phone",
                    "name": "site_phone",
                    "aria-label": "",
                    "type": "text",
                    "instructions": "",
                    "required": 0,
                    "conditional_logic": 0,
                    "wrapper": {
                        "width": "33",
                        "class": "",
                        "id": ""
                    },
                    "default_value": "",
                    "maxlength": "",
                    "placeholder": "",
                    "prepend": "",
                    "append": ""
                },
                {
                    "key": "field_653c7d1e5302f",
                    "label": "Email",
                    "name": "site_email",
                    "aria-label": "",
                    "type": "text",
                    "instructions": "",
                    "required": 0,
                    "conditional_logic": 0,
                    "wrapper": {
                        "width": "33",
                        "class": "",
                        "id": ""
                    },
                    "default_value": "",
                    "maxlength": "",
                    "placeholder": "",
                    "prepend": "",
                    "append": ""
                },
                {
                    "key": "field_6545b837fa755",
                    "label": "Address",
                    "name": "site_address",
                    "aria-label": "",
                    "type": "text",
                    "instructions": "",
                    "required": 0,
                    "conditional_logic": 0,
                    "wrapper": {
                        "width": "33",
                        "class": "",
                        "id": ""
                    },
                    "default_value": "",
                    "maxlength": "",
                    "placeholder": "",
                    "prepend": "",
                    "append": ""
                },
                {
                    "key": "field_653c7d8c53031",
                    "label": "Socials",
                    "name": "site_socials",
                    "aria-label": "",
                    "type": "repeater",
                    "instructions": "",
                    "required": 0,
                    "conditional_logic": 0,
                    "wrapper": {
                        "width": "50",
                        "class": "",
                        "id": ""
                    },
                    "layout": "table",
                    "pagination": 0,
                    "min": 0,
                    "max": 0,
                    "collapsed": "",
                    "button_label": "Add Row",
                    "rows_per_page": 20,
                    "sub_fields": [
                        {
                            "key": "field_653c7dab53032",
                            "label": "Social",
                            "name": "social",
                            "aria-label": "",
                            "type": "select",
                            "instructions": "",
                            "required": 0,
                            "conditional_logic": 0,
                            "wrapper": {
                                "width": "50",
                                "class": "",
                                "id": ""
                            },
                            "choices": {
                                "facebook": "Facebook",
                                "twitter": "Twitter",
                                "instagram": "Instagram",
                                "pinterest": "Pinterest",
                                "youtube": "Youtube"
                            },
                            "default_value": false,
                            "return_format": "value",
                            "multiple": 0,
                            "allow_null": 0,
                            "allow_in_bindings": 1,
                            "ui": 0,
                            "ajax": 0,
                            "placeholder": "",
                            "parent_repeater": "field_653c7d8c53031",
                            "create_options": 0,
                            "save_options": 0
                        },
                        {
                            "key": "field_653c7dcf53033",
                            "label": "Link",
                            "name": "link",
                            "aria-label": "",
                            "type": "text",
                            "instructions": "",
                            "required": 0,
                            "conditional_logic": 0,
                            "wrapper": {
                                "width": "50",
                                "class": "",
                                "id": ""
                            },
                            "default_value": "",
                            "maxlength": "",
                            "placeholder": "",
                            "prepend": "",
                            "append": "",
                            "parent_repeater": "field_653c7d8c53031"
                        }
                    ]
                }
            ]
        },
        {
            "key": "field_65961365e7b6a",
            "label": "Title Bar",
            "name": "",
            "aria-label": "",
            "type": "tab",
            "instructions": "",
            "required": 0,
            "conditional_logic": 0,
            "wrapper": {
                "width": "",
                "class": "",
                "id": ""
            },
            "placement": "top",
            "endpoint": 0,
            "selected": 0
        },
        {
            "key": "field_6596156f5110b",
            "label": "Background Color",
            "name": "title_bar_bg_color",
            "aria-label": "",
            "type": "color_picker",
            "instructions": "",
            "required": 0,
            "conditional_logic": 0,
            "wrapper": {
                "width": "33",
                "class": "",
                "id": ""
            },
            "default_value": "",
            "enable_opacity": 1,
            "return_format": "string",
            "allow_in_bindings": 1,
            "custom_palette_source": "",
            "palette_colors": "",
            "show_color_wheel": true
        },
        {
            "key": "field_675ceb80071b8",
            "label": "Background Images",
            "name": "title_bar_bg_images",
            "aria-label": "",
            "type": "image",
            "instructions": "",
            "required": 0,
            "conditional_logic": 0,
            "wrapper": {
                "width": "33",
                "class": "",
                "id": ""
            },
            "return_format": "array",
            "library": "all",
            "min_width": "",
            "min_height": "",
            "min_size": "",
            "max_width": "",
            "max_height": "",
            "max_size": "",
            "mime_types": "",
            "preview_size": "medium"
        },
        {
            "key": "field_675cf0a0fdb97",
            "label": "Background Overlay",
            "name": "title_bar_bg_overlay",
            "aria-label": "",
            "type": "color_picker",
            "instructions": "",
            "required": 0,
            "conditional_logic": 0,
            "wrapper": {
                "width": "34",
                "class": "",
                "id": ""
            },
            "default_value": "",
            "enable_opacity": 1,
            "return_format": "string",
            "custom_palette_source": "",
            "palette_colors": "",
            "show_color_wheel": true
        },
        {
            "key": "field_6808478307654",
            "label": "Single Post",
            "name": "",
            "aria-label": "",
            "type": "tab",
            "instructions": "",
            "required": 0,
            "conditional_logic": 0,
            "wrapper": {
                "width": "",
                "class": "",
                "id": ""
            },
            "placement": "top",
            "endpoint": 0,
            "selected": 0
        },
        {
            "key": "field_680847a407655",
            "label": "Enable Related Posts",
            "name": "enable_related_posts",
            "aria-label": "",
            "type": "true_false",
            "instructions": "",
            "required": 0,
            "conditional_logic": 0,
            "wrapper": {
                "width": "",
                "class": "",
                "id": ""
            },
            "message": "",
            "default_value": 0,
            "allow_in_bindings": 1,
            "ui_on_text": "",
            "ui_off_text": "",
            "ui": 1
        },
        {
            "key": "field_680847b907656",
            "label": "Related Post",
            "name": "related_posts",
            "aria-label": "",
            "type": "group",
            "instructions": "",
            "required": 0,
            "conditional_logic": [
                [
                    {
                        "field": "field_680847a407655",
                        "operator": "==",
                        "value": "1"
                    }
                ]
            ],
            "wrapper": {
                "width": "",
                "class": "",
                "id": ""
            },
            "layout": "block",
            "sub_fields": [
                {
                    "key": "field_680847b907657",
                    "label": "Heading",
                    "name": "heading",
                    "aria-label": "",
                    "type": "text",
                    "instructions": "",
                    "required": 0,
                    "conditional_logic": 0,
                    "wrapper": {
                        "width": "50",
                        "class": "",
                        "id": ""
                    },
                    "default_value": "",
                    "maxlength": "",
                    "allow_in_bindings": 1,
                    "placeholder": "",
                    "prepend": "",
                    "append": ""
                },
                {
                    "key": "field_680848e572e6f",
                    "label": "Description",
                    "name": "description",
                    "aria-label": "",
                    "type": "text",
                    "instructions": "",
                    "required": 0,
                    "conditional_logic": 0,
                    "wrapper": {
                        "width": "50",
                        "class": "",
                        "id": ""
                    },
                    "default_value": "",
                    "maxlength": "",
                    "allow_in_bindings": 1,
                    "placeholder": "",
                    "prepend": "",
                    "append": ""
                },
                {
                    "key": "field_680847b907658",
                    "label": "Nubmer Posts",
                    "name": "number_posts",
                    "aria-label": "",
                    "type": "number",
                    "instructions": "",
                    "required": 0,
                    "conditional_logic": 0,
                    "wrapper": {
                        "width": "100",
                        "class": "",
                        "id": ""
                    },
                    "default_value": "",
                    "min": "",
                    "max": "",
                    "allow_in_bindings": 1,
                    "placeholder": "",
                    "step": "",
                    "prepend": "",
                    "append": ""
                }
            ]
        },
        {
            "key": "field_65ab1d4bc41ad",
            "label": "Extras",
            "name": "",
            "aria-label": "",
            "type": "tab",
            "instructions": "",
            "required": 0,
            "conditional_logic": 0,
            "wrapper": {
                "width": "",
                "class": "",
                "id": ""
            },
            "placement": "top",
            "endpoint": 0,
            "selected": 0
        },
        {
            "key": "field_65ab1d62c41ae",
            "label": "Dev Mode",
            "name": "dev_mode",
            "aria-label": "",
            "type": "true_false",
            "instructions": "",
            "required": 0,
            "conditional_logic": 0,
            "wrapper": {
                "width": "",
                "class": "",
                "id": ""
            },
            "message": "",
            "default_value": 0,
            "ui_on_text": "",
            "ui_off_text": "",
            "ui": 1
        },
        {
            "key": "field_668f3cb0c5414",
            "label": "Custom Css Code",
            "name": "custom_css_code",
            "aria-label": "",
            "type": "textarea",
            "instructions": "",
            "required": 0,
            "conditional_logic": [
                [
                    {
                        "field": "field_65ab1d62c41ae",
                        "operator": "==",
                        "value": "1"
                    }
                ]
            ],
            "wrapper": {
                "width": "",
                "class": "",
                "id": ""
            },
            "default_value": "",
            "maxlength": "",
            "rows": "",
            "placeholder": "",
            "new_lines": ""
        },
        {
            "key": "field_668f40328f0b2",
            "label": "Custom Js Code",
            "name": "custom_js_code",
            "aria-label": "",
            "type": "textarea",
            "instructions": "",
            "required": 0,
            "conditional_logic": [
                [
                    {
                        "field": "field_65ab1d62c41ae",
                        "operator": "==",
                        "value": "1"
                    }
                ]
            ],
            "wrapper": {
                "width": "",
                "class": "",
                "id": ""
            },
            "default_value": "",
            "maxlength": "",
            "rows": "",
            "placeholder": "",
            "new_lines": ""
        }
    ],
    "location": [
        [
            {
                "param": "options_page",
                "operator": "==",
                "value": "theme-options-page"
            }
        ]
    ],
    "menu_order": 0,
    "position": "normal",
    "style": "default",
    "label_placement": "top",
    "instruction_placement": "label",
    "hide_on_screen": "",
    "active": true,
    "description": "",
    "show_in_rest": 0,
    "display_title": "",
    "modified": 1767155443
}
